h4u/__init__.py
h4u/courses.py
h4u/utils.py
h4u-1.0.3.dist-info/METADATA
h4u-1.0.3.dist-info/WHEEL
h4u-1.0.3.dist-info/top_level.txt
h4u-1.0.3.dist-info/RECORD
