Metadata-Version: 2.4
Name: h4u
Version: 1.0.3
Summary: Una biblioteca ficticia para consultar cursos fitcticios con links a paginas publicas no relacionadas.
Home-page: https://www.proventutprials.org/
Author: Jhonnas Iriarte
Dynamic: author
Dynamic: description
Dynamic: description-content-type
Dynamic: home-page
Dynamic: summary
